odoo/addons/helpdesk_mgmtsystem_nonconformity/README.rst
odoo/addons/helpdesk_mgmtsystem_nonconformity/__init__.py
odoo/addons/helpdesk_mgmtsystem_nonconformity/__manifest__.py
odoo/addons/helpdesk_mgmtsystem_nonconformity/data/helpdesk_ticket_stage.xml
odoo/addons/helpdesk_mgmtsystem_nonconformity/i18n/es.po
odoo/addons/helpdesk_mgmtsystem_nonconformity/i18n/helpdesk_mgmtsystem_nonconformity.pot
odoo/addons/helpdesk_mgmtsystem_nonconformity/models/__init__.py
odoo/addons/helpdesk_mgmtsystem_nonconformity/models/helpdesk_ticket.py
odoo/addons/helpdesk_mgmtsystem_nonconformity/models/helpdesk_ticket_stage.py
odoo/addons/helpdesk_mgmtsystem_nonconformity/models/mgmtsystem_nonconformity.py
odoo/addons/helpdesk_mgmtsystem_nonconformity/readme/CONTRIBUTORS.rst
odoo/addons/helpdesk_mgmtsystem_nonconformity/readme/DESCRIPTION.rst
odoo/addons/helpdesk_mgmtsystem_nonconformity/static/description/icon.png
odoo/addons/helpdesk_mgmtsystem_nonconformity/static/description/index.html
odoo/addons/helpdesk_mgmtsystem_nonconformity/tests/__init__.py
odoo/addons/helpdesk_mgmtsystem_nonconformity/tests/test_mgmtsystem_nonconformity.py
odoo/addons/helpdesk_mgmtsystem_nonconformity/views/helpdesk_ticket_stage_view.xml
odoo/addons/helpdesk_mgmtsystem_nonconformity/views/helpdesk_ticket_view.xml
odoo/addons/helpdesk_mgmtsystem_nonconformity/views/mgmtsystem_nonconformity_view.xml
odoo13_addon_helpdesk_mgmtsystem_nonconformity-13.0.1.0.1.dist-info/METADATA
odoo13_addon_helpdesk_mgmtsystem_nonconformity-13.0.1.0.1.dist-info/WHEEL
odoo13_addon_helpdesk_mgmtsystem_nonconformity-13.0.1.0.1.dist-info/top_level.txt
odoo13_addon_helpdesk_mgmtsystem_nonconformity-13.0.1.0.1.dist-info/RECORD
